{
  "odm_georeferenced_model.laz": {
    "bounds": [
      210352.2052154541,
      9670930.93542707,
      25.020845413208008,
      210368.4152355194,
      9670953.069719315,
      66.18449401855469
    ],
    "metadata": {
      "comp_spatialreference": "PROJCS[\"WGS 84 / UTM zone 50S\",GEOGCS[\"WGS 84\",DATUM[\"WGS_1984\",SPHEROID[\"WGS 84\",6378137,298.257223563,AUTHORITY[\"EPSG\",\"7030\"]],AUTHORITY[\"EPSG\",\"6326\"]],PRIMEM[\"Greenwich\",0,AUTHORITY[\"EPSG\",\"8901\"]],UNIT[\"degree\",0.0174532925199433,AUTHORITY[\"EPSG\",\"9122\"]],AUTHORITY[\"EPSG\",\"4326\"]],PROJECTION[\"Transverse_Mercator\"],PARAMETER[\"latitude_of_origin\",0],PARAMETER[\"central_meridian\",117],PARAMETER[\"scale_factor\",0.9996],PARAMETER[\"false_easting\",500000],PARAMETER[\"false_northing\",10000000],UNIT[\"metre\",1,AUTHORITY[\"EPSG\",\"9001\"]],AXIS[\"Easting\",EAST],AXIS[\"Northing\",NORTH],AUTHORITY[\"EPSG\",\"32750\"]]",
      "compressed": true,
      "count": 180218,
      "creation_doy": 285,
      "creation_year": 2021,
      "dataformat_id": 3,
      "dataoffset": 522,
      "filesource_id": 0,
      "global_encoding": 0,
      "global_encoding_base64": "AAA=",
      "header_size": 227,
      "major_version": 1,
      "maxx": 210368.4152,
      "maxy": 9670953.07,
      "maxz": 66.18449402,
      "minor_version": 2,
      "minx": 210352.2052,
      "miny": 9670930.935,
      "minz": 25.02084541,
      "offset_x": 210378,
      "offset_y": 9670929,
      "offset_z": 0,
      "point_length": 34,
      "project_id": "00000000-0000-0000-0000-000000000000",
      "scale_x": 0.01,
      "scale_y": 0.01,
      "scale_z": 0.01,
      "software_id": "PDAL 2.2.0 (Releas)",
      "spatialreference": "PROJCS[\"WGS 84 / UTM zone 50S\",GEOGCS[\"WGS 84\",DATUM[\"WGS_1984\",SPHEROID[\"WGS 84\",6378137,298.257223563,AUTHORITY[\"EPSG\",\"7030\"]],AUTHORITY[\"EPSG\",\"6326\"]],PRIMEM[\"Greenwich\",0,AUTHORITY[\"EPSG\",\"8901\"]],UNIT[\"degree\",0.0174532925199433,AUTHORITY[\"EPSG\",\"9122\"]],AUTHORITY[\"EPSG\",\"4326\"]],PROJECTION[\"Transverse_Mercator\"],PARAMETER[\"latitude_of_origin\",0],PARAMETER[\"central_meridian\",117],PARAMETER[\"scale_factor\",0.9996],PARAMETER[\"false_easting\",500000],PARAMETER[\"false_northing\",10000000],UNIT[\"metre\",1,AUTHORITY[\"EPSG\",\"9001\"]],AXIS[\"Easting\",EAST],AXIS[\"Northing\",NORTH],AUTHORITY[\"EPSG\",\"32750\"]]",
      "srs": {
        "compoundwkt": "PROJCS[\"WGS 84 / UTM zone 50S\",GEOGCS[\"WGS 84\",DATUM[\"WGS_1984\",SPHEROID[\"WGS 84\",6378137,298.257223563,AUTHORITY[\"EPSG\",\"7030\"]],AUTHORITY[\"EPSG\",\"6326\"]],PRIMEM[\"Greenwich\",0,AUTHORITY[\"EPSG\",\"8901\"]],UNIT[\"degree\",0.0174532925199433,AUTHORITY[\"EPSG\",\"9122\"]],AUTHORITY[\"EPSG\",\"4326\"]],PROJECTION[\"Transverse_Mercator\"],PARAMETER[\"latitude_of_origin\",0],PARAMETER[\"central_meridian\",117],PARAMETER[\"scale_factor\",0.9996],PARAMETER[\"false_easting\",500000],PARAMETER[\"false_northing\",10000000],UNIT[\"metre\",1,AUTHORITY[\"EPSG\",\"9001\"]],AXIS[\"Easting\",EAST],AXIS[\"Northing\",NORTH],AUTHORITY[\"EPSG\",\"32750\"]]",
        "horizontal": "PROJCS[\"WGS 84 / UTM zone 50S\",GEOGCS[\"WGS 84\",DATUM[\"WGS_1984\",SPHEROID[\"WGS 84\",6378137,298.257223563,AUTHORITY[\"EPSG\",\"7030\"]],AUTHORITY[\"EPSG\",\"6326\"]],PRIMEM[\"Greenwich\",0,AUTHORITY[\"EPSG\",\"8901\"]],UNIT[\"degree\",0.0174532925199433,AUTHORITY[\"EPSG\",\"9122\"]],AUTHORITY[\"EPSG\",\"4326\"]],PROJECTION[\"Transverse_Mercator\"],PARAMETER[\"latitude_of_origin\",0],PARAMETER[\"central_meridian\",117],PARAMETER[\"scale_factor\",0.9996],PARAMETER[\"false_easting\",500000],PARAMETER[\"false_northing\",10000000],UNIT[\"metre\",1,AUTHORITY[\"EPSG\",\"9001\"]],AXIS[\"Easting\",EAST],AXIS[\"Northing\",NORTH],AUTHORITY[\"EPSG\",\"32750\"]]",
        "isgeocentric": false,
        "isgeographic": false,
        "prettycompoundwkt": "PROJCS[\"WGS 84 / UTM zone 50S\",\n    GEOGCS[\"WGS 84\",\n        DATUM[\"WGS_1984\",\n            SPHEROID[\"WGS 84\",6378137,298.257223563,\n                AUTHORITY[\"EPSG\",\"7030\"]],\n            AUTHORITY[\"EPSG\",\"6326\"]],\n        PRIMEM[\"Greenwich\",0,\n            AUTHORITY[\"EPSG\",\"8901\"]],\n        UNIT[\"degree\",0.0174532925199433,\n            AUTHORITY[\"EPSG\",\"9122\"]],\n        AUTHORITY[\"EPSG\",\"4326\"]],\n    PROJECTION[\"Transverse_Mercator\"],\n    PARAMETER[\"latitude_of_origin\",0],\n    PARAMETER[\"central_meridian\",117],\n    PARAMETER[\"scale_factor\",0.9996],\n    PARAMETER[\"false_easting\",500000],\n    PARAMETER[\"false_northing\",10000000],\n    UNIT[\"metre\",1,\n        AUTHORITY[\"EPSG\",\"9001\"]],\n    AXIS[\"Easting\",EAST],\n    AXIS[\"Northing\",NORTH],\n    AUTHORITY[\"EPSG\",\"32750\"]]",
        "prettywkt": "PROJCS[\"WGS 84 / UTM zone 50S\",\n    GEOGCS[\"WGS 84\",\n        DATUM[\"WGS_1984\",\n            SPHEROID[\"WGS 84\",6378137,298.257223563,\n                AUTHORITY[\"EPSG\",\"7030\"]],\n            AUTHORITY[\"EPSG\",\"6326\"]],\n        PRIMEM[\"Greenwich\",0,\n            AUTHORITY[\"EPSG\",\"8901\"]],\n        UNIT[\"degree\",0.0174532925199433,\n            AUTHORITY[\"EPSG\",\"9122\"]],\n        AUTHORITY[\"EPSG\",\"4326\"]],\n    PROJECTION[\"Transverse_Mercator\"],\n    PARAMETER[\"latitude_of_origin\",0],\n    PARAMETER[\"central_meridian\",117],\n    PARAMETER[\"scale_factor\",0.9996],\n    PARAMETER[\"false_easting\",500000],\n    PARAMETER[\"false_northing\",10000000],\n    UNIT[\"metre\",1,\n        AUTHORITY[\"EPSG\",\"9001\"]],\n    AXIS[\"Easting\",EAST],\n    AXIS[\"Northing\",NORTH],\n    AUTHORITY[\"EPSG\",\"32750\"]]",
        "proj4": "+proj=utm +zone=50 +south +datum=WGS84 +units=m +no_defs",
        "units": {
          "horizontal": "metre",
          "vertical": ""
        },
        "vertical": "",
        "wkt": "PROJCS[\"WGS 84 / UTM zone 50S\",GEOGCS[\"WGS 84\",DATUM[\"WGS_1984\",SPHEROID[\"WGS 84\",6378137,298.257223563,AUTHORITY[\"EPSG\",\"7030\"]],AUTHORITY[\"EPSG\",\"6326\"]],PRIMEM[\"Greenwich\",0,AUTHORITY[\"EPSG\",\"8901\"]],UNIT[\"degree\",0.0174532925199433,AUTHORITY[\"EPSG\",\"9122\"]],AUTHORITY[\"EPSG\",\"4326\"]],PROJECTION[\"Transverse_Mercator\"],PARAMETER[\"latitude_of_origin\",0],PARAMETER[\"central_meridian\",117],PARAMETER[\"scale_factor\",0.9996],PARAMETER[\"false_easting\",500000],PARAMETER[\"false_northing\",10000000],UNIT[\"metre\",1,AUTHORITY[\"EPSG\",\"9001\"]],AXIS[\"Easting\",EAST],AXIS[\"Northing\",NORTH],AUTHORITY[\"EPSG\",\"32750\"]]"
      },
      "system_id": "PDAL",
      "vlr_0": {
        "data": "AQABAAAABwAABAAAAQABAAEEAAABAAEAAgSxhwgAAAABCLGHCAAIAAYIAAABAI4jAAwAAAEA7n8EDAAAAQApIw==",
        "description": "GeoTiff GeoKeyDirectoryTag",
        "record_id": 34735,
        "user_id": "LASF_Projection"
      },
      "vlr_1": {
        "data": "dW5rbm93bnx1bmtub3dufAA=",
        "description": "GeoTiff GeoAsciiParamsTag",
        "record_id": 34737,
        "user_id": "LASF_Projection"
      },
      "vlr_2": {
        "data": "AgAAAAMBAAAAAAAAUMMAAP////////////////////8DAAYAFAACAAcACAACAAgABgACAA==",
        "description": "http://laszip.org",
        "record_id": 22204,
        "user_id": "laszip encoded"
      }
    },
    "origin": 0,
    "points": 180218,
    "srs": {
      "authority": "EPSG",
      "horizontal": "32750",
      "wkt": "PROJCS[\"WGS 84 / UTM zone 50S\",GEOGCS[\"WGS 84\",DATUM[\"WGS_1984\",SPHEROID[\"WGS 84\",6378137,298.257223563,AUTHORITY[\"EPSG\",\"7030\"]],AUTHORITY[\"EPSG\",\"6326\"]],PRIMEM[\"Greenwich\",0,AUTHORITY[\"EPSG\",\"8901\"]],UNIT[\"degree\",0.0174532925199433,AUTHORITY[\"EPSG\",\"9122\"]],AUTHORITY[\"EPSG\",\"4326\"]],PROJECTION[\"Transverse_Mercator\"],PARAMETER[\"latitude_of_origin\",0],PARAMETER[\"central_meridian\",117],PARAMETER[\"scale_factor\",0.9996],PARAMETER[\"false_easting\",500000],PARAMETER[\"false_northing\",10000000],UNIT[\"metre\",1,AUTHORITY[\"EPSG\",\"9001\"]],AXIS[\"Easting\",EAST],AXIS[\"Northing\",NORTH],AUTHORITY[\"EPSG\",\"32750\"]]"
    }
  }
}